[
    {
        "id": "435-43e-3fe-41e",
        "title": "Add Users To Your Node Api",
        "author": "Brilliant Dude",
        "bookQuantity": 6,
        "rentedQuantity": 0,
        "description": "sighsss. dolor sit amet, consectetur adipiscing elit. Vestibulum luctus dolor sit amet orci vulputate malesuada. Lorem ipsum dolor sit."
    },
    {
        "id": "400-3ff-40d-404",
        "title": "Add Users To Your Node Api",
        "author": "Brilliant Dude",
        "bookQuantity": 6,
        "rentedQuantity": 0,
        "description": "sighsss. dolor sit amet, consectetur adipiscing elit. Vestibulum luctus dolor sit amet orci vulputate malesuada. Lorem ipsum dolor sit."
    },
    {
        "id": "448-442-3f8-42b",
        "title": "How to write a node article",
        "author": "Brilliant Dude",
        "bookQuantity": 6,
        "rentedQuantity": 0,
        "description": "sighsss. dolor sit amet, consectetur adipiscing elit. Vestibulum luctus dolor sit amet orci vulputate malesuada. Lorem ipsum dolor sit."
    },
    {
        "id": "437-433-43a-3fb",
        "title": "How to write a node article",
        "author": "Brilliant Dude",
        "bookQuantity": 6,
        "rentedQuantity": 0,
        "description": "sighsss. dolor sit amet, consectetur adipiscing elit. Vestibulum luctus dolor sit amet orci vulputate malesuada. Lorem ipsum dolor sit."
    },
    {
        "id": "3ea-444-44b-43c",
        "title": "Add Users To Your Node Api",
        "author": "Brilliant Dude",
        "bookQuantity": 2,
        "rentedQuantity": 0,
        "description": "sighsss. dolor sit amet, consectetur adipiscing elit. Vestibulum luctus dolor sit amet orci vulputate malesuada. Lorem ipsum dolor sit."
    },
    {
        "id": "43d-3ec-411-44b",
        "title": "How to write a node article",
        "author": "Brilliant Dude",
        "bookQuantity": 6,
        "rentedQuantity": 0,
        "description": "sighsss. dolor sit amet, consectetur adipiscing elit. Vestibulum luctus dolor sit amet orci vulputate malesuada. Lorem ipsum dolor sit."
    },
    {
        "id": "3ff-41a-40b-413",
        "title": "How to write a node article",
        "author": "Brilliant Dude",
        "bookQuantity": 6,
        "rentedQuantity": 0,
        "description": "sighsss. dolor sit amet, consectetur adipiscing elit. Vestibulum luctus dolor sit amet orci vulputate malesuada. Lorem ipsum dolor sit."
    },
    {
        "id": "3f8-43d-42a-444",
        "title": "Add Users To Your Node Api",
        "author": "Brilliant Dude",
        "bookQuantity": 2,
        "rentedQuantity": 0,
        "description": "sighsss. dolor sit amet, consectetur adipiscing elit. Vestibulum luctus dolor sit amet orci vulputate malesuada. Lorem ipsum dolor sit."
    }
]